LICENSE
MANIFEST.in
README.rst
apc-nrp.php
setup.py
etc/init.d/newrelic-plugin-agent.deb
etc/init.d/newrelic-plugin-agent.rhel
etc/newrelic/newrelic-plugin-agent.cfg
newrelic_plugin_agent/__init__.py
newrelic_plugin_agent/agent.py
newrelic_plugin_agent.egg-info/PKG-INFO
newrelic_plugin_agent.egg-info/SOURCES.txt
newrelic_plugin_agent.egg-info/dependency_links.txt
newrelic_plugin_agent.egg-info/entry_points.txt
newrelic_plugin_agent.egg-info/requires.txt
newrelic_plugin_agent.egg-info/top_level.txt
newrelic_plugin_agent/plugins/__init__.py
newrelic_plugin_agent/plugins/apache_httpd.py
newrelic_plugin_agent/plugins/base.py
newrelic_plugin_agent/plugins/couchdb.py
newrelic_plugin_agent/plugins/elasticsearch.py
newrelic_plugin_agent/plugins/haproxy.py
newrelic_plugin_agent/plugins/memcached.py
newrelic_plugin_agent/plugins/mongodb.py
newrelic_plugin_agent/plugins/nginx.py
newrelic_plugin_agent/plugins/pgbouncer.py
newrelic_plugin_agent/plugins/php_apc.py
newrelic_plugin_agent/plugins/php_fpm.py
newrelic_plugin_agent/plugins/postgresql.py
newrelic_plugin_agent/plugins/rabbitmq.py
newrelic_plugin_agent/plugins/redis.py
newrelic_plugin_agent/plugins/riak.py
newrelic_plugin_agent/plugins/uwsgi.py